tenminutevpn/__init__.py
tenminutevpn/network.py
tenminutevpn/wireguard.py
tenminutevpn-0.2.0.dist-info/LICENSE
tenminutevpn-0.2.0.dist-info/METADATA
tenminutevpn-0.2.0.dist-info/WHEEL
tenminutevpn-0.2.0.dist-info/entry_points.txt
tenminutevpn-0.2.0.dist-info/top_level.txt
tenminutevpn-0.2.0.dist-info/RECORD
