Metadata-Version: 2.1
Name: tenminutevpn
Version: 0.2.0
Summary: TenMinuteVPN
Author-email: Andrey Gubarev <andrey@andreygubarev.com>
License: BSD
Project-URL: Homepage, https://github.com/andreygubarev/tenminutevpn/
License-File: LICENSE
Requires-Dist: pyroute2 ==0.7.2
Requires-Dist: serfio ==0.3.3
Requires-Dist: msgpack ==1.0.3
